winpwn/__init__.py
winpwn/context.py
winpwn/dbg.py
winpwn/misc.py
winpwn/var.py
winpwn/win.py
winpwn/winpwn.py
iotpwn-0.0.1.dist-info/METADATA
iotpwn-0.0.1.dist-info/WHEEL
iotpwn-0.0.1.dist-info/top_level.txt
iotpwn-0.0.1.dist-info/RECORD
